scportal_lib/__init__.py
scportal_lib/analytics.py
supplychain_portal_lib-0.1.0.dist-info/METADATA
supplychain_portal_lib-0.1.0.dist-info/WHEEL
supplychain_portal_lib-0.1.0.dist-info/top_level.txt
supplychain_portal_lib-0.1.0.dist-info/RECORD
