Metadata-Version: 2.4
Name: supplychain-portal-lib
Version: 0.1.0
Summary: Analytics helpers for Supply Chain Portal bookings
Home-page: https://pypi.org/project/supplychain-portal-lib/
Author: Vishnu Vardhan
Author-email: adnvishnu@gmail.com
Requires-Python: >=3.8
Dynamic: author
Dynamic: author-email
Dynamic: home-page
Dynamic: requires-python
Dynamic: summary
